{
  "project_info": {
    "project_number": "494425200027",
    "project_id": "weather-studying-gb",
    "storage_bucket": "weather-studying-gb.appspot.com"
  },
  "client": [
    {
      "client_info": {
        "mobilesdk_app_id": "1:494425200027:android:9ba0bddb4fb0a3c8b8fd3e",
        "android_client_info": {
          "package_name": "com.example.chotamnaulitce"
        }
      },
      "oauth_client": [
        {
          "client_id": "494425200027-2e1vs4k7l0v7fd8m8i1uhe3qe1danijf.apps.googleusercontent.com",
          "client_type": 1,
          "android_info": {
            "package_name": "com.example.chotamnaulitce",
            "certificate_hash": "88b067a0cc4b2de421e75396f297f5338a411a09"
          }
        },
        {
          "client_id": "494425200027-oceh6l3q503d77o8vdpg556prskk9cu0.apps.googleusercontent.com",
          "client_type": 3
        }
      ],
      "api_key": [
        {
          "current_key": "AIzaSyBhs0Ac_bZlh7HAkeLHta9iynI5ro6-mbc"
        }
      ],
      "services": {
        "appinvite_service": {
          "other_platform_oauth_client": [
            {
              "client_id": "494425200027-oceh6l3q503d77o8vdpg556prskk9cu0.apps.googleusercontent.com",
              "client_type": 3
            }
          ]
        }
      }
    }
  ],
  "configuration_version": "1"
}